airportfinder/__init__.py
airportfinder/airportfinder.py
airportfinder/data/airports.json
airportfinder-1.0.0.dist-info/LICENSE
airportfinder-1.0.0.dist-info/METADATA
airportfinder-1.0.0.dist-info/WHEEL
airportfinder-1.0.0.dist-info/top_level.txt
airportfinder-1.0.0.dist-info/RECORD
