Metadata-Version: 2.1
Name: airportfinder
Version: 1.0.0
Summary: Python library for airport lookup by IATA code or name
Home-page: https://github.com/EzeTP/airportfinder
Author: Ezequiel Tejada
Classifier: License :: OSI Approved :: BSD License
Classifier: Programming Language :: Python :: 3
Classifier: Programming Language :: Python :: 3.7
Classifier: Programming Language :: Python :: 3.8
Classifier: Programming Language :: Python :: 3.9
Requires-Python: >=3.7
License-File: LICENSE
Requires-Dist: requests
